contrast_route_duplicates/__init__.py
contrast_route_duplicates/__main__.py
contrast_route_duplicates/analyzer.py
contrast_route_duplicates/cli.py
contrast_route_duplicates/config.py
contrast_route_duplicates/exceptions.py
contrast_route_duplicates/models.py
contrast_route_duplicates/resilient.py
contrast_route_duplicates/utils.py
contrast_route_duplicates-0.1.6.dist-info/METADATA
contrast_route_duplicates-0.1.6.dist-info/WHEEL
contrast_route_duplicates-0.1.6.dist-info/entry_points.txt
contrast_route_duplicates-0.1.6.dist-info/RECORD
