Metadata-Version: 2.3
Name: contrast-route-duplicates
Version: 0.1.6
Summary: A command-line tool for analyzing duplicate route signatures in Contrast Security applications.
Author-email: Jonathan Harper <39912347+jharper-sec@users.noreply.github.com>
Requires-Python: >=3.8
Requires-Dist: black>=24.10.0
Requires-Dist: httpx>=0.27.2
Requires-Dist: python-dotenv>=1.0.1
Requires-Dist: rich>=13.9.4
Requires-Dist: tqdm>=4.67.0
Requires-Dist: typer>=0.13.1
